pretlog/__init__.py
pretlog/col.py
pretlog-0.1.2.dist-info/COPYING
pretlog-0.1.2.dist-info/LICENSE
pretlog-0.1.2.dist-info/METADATA
pretlog-0.1.2.dist-info/WHEEL
pretlog-0.1.2.dist-info/top_level.txt
pretlog-0.1.2.dist-info/RECORD
